.DS_Store
dimcli/.DS_Store
dimcli/VERSION.py
dimcli/__init__.py
dimcli/functions.py
dimcli/main_cli.py
dimcli/shortcuts.py
dimcli/core/__init__.py
dimcli/core/api.py
dimcli/core/auth.py
dimcli/core/converters.py
dimcli/core/dataframe_factory.py
dimcli/core/dsl_grammar.py
dimcli/core/dsl_grammar_categories.py
dimcli/core/dsl_grammar_core.py
dimcli/core/dsl_grammar_core_BK.py
dimcli/core/dsl_grammar_extras.py
dimcli/core/extras.py
dimcli/core/functions.py
dimcli/jupyter/__init__.py
dimcli/jupyter/magics.py
dimcli/repl/__init__.py
dimcli/repl/autocompletion.py
dimcli/repl/history.py
dimcli/repl/key_bindings.py
dimcli/repl/lexer.py
dimcli/repl/repl.py
dimcli/repl/validator.py
dimcli/templates/pyvis_inline.html
dimcli/tests/__init__.py
dimcli/tests/_test_converters.py
dimcli/tests/quicktest.py
dimcli/tests/settings.py
dimcli/tests/test_cris.py
dimcli/tests/test_dataframes.py
dimcli/tests/test_export.py
dimcli/tests/test_export_gsheets.py
dimcli/tests/test_functions.py
dimcli/tests/test_grammar.py
dimcli/tests/test_login.py
dimcli/tests/test_magics.py
dimcli/tests/test_queries.py
dimcli/utils/__init__.py
dimcli/utils/all.py
dimcli/utils/converters.py
dimcli/utils/dim_utils.py
dimcli/utils/gbq_utils.py
dimcli/utils/gists_utils.py
dimcli/utils/html.py
dimcli/utils/misc_utils.py
dimcli/utils/networkviz.py
dimcli/utils/repl_utils.py
dimcli/utils/version_utils.py
dimcli-1.6.dist-info/LICENSE
dimcli-1.6.dist-info/METADATA
dimcli-1.6.dist-info/WHEEL
dimcli-1.6.dist-info/entry_points.txt
dimcli-1.6.dist-info/top_level.txt
dimcli-1.6.dist-info/RECORD
