Metadata-Version: 2.1
Name: dimcli
Version: 1.6
Summary: Python REPL/API for accessing dimensions.ai.
Home-page: https://github.com/digital-science/dimcli
Author: Michele Pasin @lambdaman
Author-email: m.pasin@digital-science.com
License: MIT License
Platform: UNKNOWN
License-File: LICENSE
Requires-Dist: click
Requires-Dist: requests
Requires-Dist: pygments
Requires-Dist: ipython
Requires-Dist: prompt-toolkit
Requires-Dist: packaging
Requires-Dist: numpy
Requires-Dist: pandas
Requires-Dist: recommonmark
Requires-Dist: tqdm
